pwmled/__init__.py
pwmled/driver/__init__.py
pwmled/driver/gpio.py
pwmled/driver/pca9685.py
pwmled/led/__init__.py
pwmled/led/rgb.py
pwmled/led/rgbw.py
pwmled/transitions/__init__.py
pwmled/transitions/transition.py
pwmled/transitions/transition_manager.py
pwmled_ant-1.6.16.dist-info/LICENSE
pwmled_ant-1.6.16.dist-info/METADATA
pwmled_ant-1.6.16.dist-info/WHEEL
pwmled_ant-1.6.16.dist-info/top_level.txt
pwmled_ant-1.6.16.dist-info/RECORD
