Metadata-Version: 2.1
Name: pwmled-ant
Version: 1.6.16
Summary: Control LEDs connected to a micro controller using pwm.
Author-email: soldag <soren.oldag@gmail.com>
License: MIT
Project-URL: Homepage, https://github.com/soldag/python-pwmled
Project-URL: Repository, https://github.com/soldag/python-pwmled
Project-URL: Bug Tracker, https://github.com/soldag/python-pwmled/issues
Classifier: License :: OSI Approved :: MIT License
Classifier: Programming Language :: Python :: 3
Classifier: Topic :: Software Development :: Libraries :: Python Modules
Requires-Python: >=3.6
License-File: LICENSE
Requires-Dist: pigpio >=1.78
Requires-Dist: adafruit-blinka >=8.21
Requires-Dist: adafruit-circuitpython-pca9685 >=3.4.10
Requires-Dist: python-singleton >=0.1.2
Requires-Dist: RPi.GPIO ==0.7.1
